gads3/__init__.py
tests/__init__.py
tests/test_init.py
gads3-0.0.1.dist-info/LICENSE
gads3-0.0.1.dist-info/METADATA
gads3-0.0.1.dist-info/WHEEL
gads3-0.0.1.dist-info/top_level.txt
gads3-0.0.1.dist-info/RECORD
