Metadata-Version: 2.1
Name: gads3
Version: 0.0.1
Summary: An async and lightweight S3 client for uploading, downloading, and deleting files
Home-page: https://github.com/AlexDemure/gads3
Author: Alexander Grishchenko
Author-email: alexanderdemure@gmail.com
Classifier: Programming Language :: Python :: 3
Classifier: License :: OSI Approved :: MIT License
Classifier: Operating System :: OS Independent
Requires-Python: >=3.8
License-File: LICENSE
Requires-Dist: aioboto3
Requires-Dist: aiofiles
